xform/__init__.py
xform/__version__.py
xform/conftest.py
xform/bridging/__init__.py
xform/bridging/graph.py
xform/transforms/__init__.py
xform/transforms/affine.py
xform/transforms/base.py
xform/transforms/cmtk.py
xform/transforms/elastix.py
xform/transforms/h5.py
xform/transforms/moving_least_squares.py
xform/transforms/thinplate.py
xform/utils/__init__.py
xform/utils/exceptions.py
xform/utils/iterables.py
xform/utils/misc.py
xform-0.1.0.dist-info/LICENSE
xform-0.1.0.dist-info/METADATA
xform-0.1.0.dist-info/WHEEL
xform-0.1.0.dist-info/top_level.txt
xform-0.1.0.dist-info/RECORD
