Metadata-Version: 2.1
Name: xform
Version: 0.1.0
Summary: Library for transforming data
Home-page: http://xform.readthedocs.io
Author: Philipp Schlegel
Author-email: pms70@cam.ac.uk
License: GNU GPL V3
Project-URL: Documentation, http://xform.readthedocs.io
Project-URL: Source, https://github.com/schlegelp/xform
Keywords: Transform CMTK affine landmarks thin-plate spline
Classifier: Development Status :: 4 - Beta
Classifier: Intended Audience :: Science/Research
Classifier: Topic :: Scientific/Engineering :: Bio-Informatics
Classifier: License :: OSI Approved :: GNU General Public License v3 or later (GPLv3+)
Classifier: Programming Language :: Python :: 3
Classifier: Programming Language :: Python :: 3.7
Classifier: Programming Language :: Python :: 3.8
Classifier: Programming Language :: Python :: 3.9
Requires-Python: >=3.6
License-File: LICENSE
Requires-Dist: h5py >=3.1
Requires-Dist: morphops >=0.1.11
Requires-Dist: numpy >=1.16
Requires-Dist: pandas >=1.0
Requires-Dist: setuptools >=50.6
Requires-Dist: tqdm >=4.45
Requires-Dist: typing-extensions >=3.7.4
Requires-Dist: molesq >=0.2.0
Requires-Dist: fuzzywuzzy >=0.18
Requires-Dist: matplotlib >=3.2
Requires-Dist: networkx >=2.4
Requires-Dist: seaborn >=0.10
Provides-Extra: all
Provides-Extra: all-dev
Requires-Dist: flake8 ; extra == 'all-dev'
Requires-Dist: wheel ; extra == 'all-dev'
Requires-Dist: mypy ; extra == 'all-dev'
Requires-Dist: pytest ; extra == 'all-dev'
Requires-Dist: pytest-env ; extra == 'all-dev'
Requires-Dist: pytest-xvfb ; extra == 'all-dev'
Requires-Dist: gitpython ; extra == 'all-dev'
Provides-Extra: dev
Requires-Dist: flake8 ; extra == 'dev'
Requires-Dist: wheel ; extra == 'dev'
Requires-Dist: mypy ; extra == 'dev'
Requires-Dist: pytest ; extra == 'dev'
Requires-Dist: pytest-env ; extra == 'dev'
Requires-Dist: pytest-xvfb ; extra == 'dev'
Requires-Dist: gitpython ; extra == 'dev'
